tektronixosc/__init__.py
tektronixosc/oscilloscope.py
tektronixosc-0.2.0.dist-info/AUTHORS.rst
tektronixosc-0.2.0.dist-info/LICENSE
tektronixosc-0.2.0.dist-info/METADATA
tektronixosc-0.2.0.dist-info/WHEEL
tektronixosc-0.2.0.dist-info/top_level.txt
tektronixosc-0.2.0.dist-info/RECORD
