Metadata-Version: 2.2
Name: tektronixosc
Version: 0.2.0
Summary: Interface for Tektronix Oscilloscopes.
Home-page: https://github.com/BMecke/tektronixosc
Author: Bruno Mecke
Author-email: info@bmecke.de
License: BSD
Classifier: Development Status :: 4 - Beta
Classifier: Intended Audience :: Science/Research
Classifier: License :: OSI Approved :: BSD License
Classifier: Programming Language :: Python :: 3
Classifier: Topic :: Scientific/Engineering
Requires-Python: >=3
License-File: LICENSE
License-File: AUTHORS.rst
Requires-Dist: pyvisa
Requires-Dist: pyvisa-py; sys_platform == "linux"
Requires-Dist: pyusb; sys_platform == "linux"
Dynamic: author
Dynamic: author-email
Dynamic: classifier
Dynamic: description
Dynamic: home-page
Dynamic: license
Dynamic: requires-dist
Dynamic: requires-python
Dynamic: summary
